niffler/__init__.py
niffler/client.py
niffler/config.py
niffler/enums.py
niffler/grammer/__init__.py
niffler/grammer/expression.py
niffler/grammer/operators.py
niffler/models/__init__.py
niffler/models/__proto__.py
niffler/models/alpha.py
niffler/models/alphaset.py
niffler/models/mixin.py
niffler/models/simulation.py
niffler/models/user.py
niffler/py.typed
niffler/strategy/__init__.py
niffler/strategy/__proto__.py
niffler/strategy/auto_ra.py
niffler/utils.py
py_niffler-0.1.0.dist-info/WHEEL
py_niffler-0.1.0.dist-info/METADATA
py_niffler-0.1.0.dist-info/RECORD
