Metadata-Version: 2.3
Name: py-niffler
Version: 0.1.0
Summary: Agent for Worldquant Brain platform.
Author: ashswing
Author-email: ashswing <ashswing@email.cn>
Requires-Dist: aerich[toml]>=0.9.2
Requires-Dist: asyncpg>=0.31.0
Requires-Dist: click>=8.3.1
Requires-Dist: httpx[socks]>=0.28.1
Requires-Dist: numpy>=2.3.5
Requires-Dist: polars>=1.36.1
Requires-Dist: pydantic>=2.12.5
Requires-Dist: pydantic-extra-types>=2.10.6
Requires-Dist: pydantic-settings>=2.12.0
Requires-Dist: tortoise-orm>=0.25.1
Requires-Python: >=3.13
